inferences/__init__.py
inferences-0.0.0.dist-info/DESCRIPTION.rst
inferences-0.0.0.dist-info/METADATA
inferences-0.0.0.dist-info/RECORD
inferences-0.0.0.dist-info/WHEEL
inferences-0.0.0.dist-info/metadata.json
inferences-0.0.0.dist-info/top_level.txt
