Metadata-Version: 2.0
Name: inferences
Version: 0.0.0
Summary: Python inference server client for humans
Home-page: https://github.com/pypa/sampleproject
Author: Openbayes
Author-email: dev@openbayes.com
License: UNKNOWN
Keywords: inference tensorrt tensorflow tf-serving pytorch onnx
Platform: UNKNOWN
Classifier: Development Status :: 3 - Alpha
Classifier: Intended Audience :: Developers
Classifier: Topic :: Software Development :: Build Tools
Classifier: License :: OSI Approved :: MIT License
Classifier: Programming Language :: Python :: 3
Classifier: Programming Language :: Python :: 3.6
Classifier: Programming Language :: Python :: 3.7
Classifier: Programming Language :: Python :: 3.8
Requires-Python: >=3.6, <4
Requires-Dist: requests
